{
  "themes": [
    {
      "id": 0,
      "name": "standard",
      "background": "/images/background.png",
      "color": {
        "text": "white",
        "button": "#1C3E97"
      },
      "fonts": {
        "title": "DM Sans",
        "body": "DM Sans"
      },
      "modal": {
        "bg": "white",
        "font": "#1C3E97"
      }
    },
    {
      "id": 1,
      "name": "valentines",
      "background": "/images/pink-bg.png",
      "color": {
        "text": "#CB2A6B",
        "button": "#CB2A6B"
      },
      "fonts": {
        "title": "josefin",
        "body": "dmsans"
      },
      "modal": {
        "bg": "white",
        "font": "#1C3E97"
      }
    }
  ]
}
